{
  "data_source": {
    "mode": "manual",
    "manual": { "timezone": "America/New_York" }
  },
  "profile": {
    "student_name": "Student",
    "school_name": "",
    "semester": "",
    "week_start": "monday"
  },
  "courses": [],
  "notifications": {
    "enabled": true,
    "reminders": [
      { "type": "before_class", "minutes": 15 }
    ],
    "quiet_hours": { "enabled": false }
  },
  "ui": {
    "theme": "system",
    "home_layout": { "sections": ["next_class", "today_overview", "week_timeline"] },
    "show_map_links": true,
    "show_instructor": true
  },
  "shortcuts": {
    "quick_actions": [
      { "id": "open_next_class_map", "label": "Open Map", "action": "map:next" }
    ]
  }
}

